pyconfighelper/__init__.py
pyconfighelper/encryptconfig.py
pyconfighelper-0.0.9.dist-info/LICENSE
pyconfighelper-0.0.9.dist-info/METADATA
pyconfighelper-0.0.9.dist-info/WHEEL
pyconfighelper-0.0.9.dist-info/top_level.txt
pyconfighelper-0.0.9.dist-info/RECORD
