Metadata-Version: 2.1
Name: pyconfighelper
Version: 0.0.9
Summary: Retrieve an encrypted JSON configuration file from Github and decrypt it. Encryption/Decryption is performed via Google Cloud KMS keys.
Home-page: http://github.com/joncain/pyconfighelper
Author: Jon Cain
Author-email: jon@joncain.net
License: Apache 2.0
Platform: UNKNOWN
Requires-Python: >=3.6
Requires-Dist: cryptography
Requires-Dist: google-cloud-kms (==1.2.1)
Requires-Dist: requests
